robotengine/__init__.py
robotengine/cli.py
robotengine/engine.py
robotengine/example.py
robotengine/help_server.py
robotengine/ho_robot.py
robotengine/input.py
robotengine/node.py
robotengine/robot_link.py
robotengine/robotlink.py
robotengine/serial_io.py
robotengine/signal.py
robotengine/state_machine.py
robotengine/timer.py
robotengine/tools.py
robotengine/docs/index.html
robotengine/docs/robotengine.html
robotengine/docs/search.js
robotengine/docs/robotengine/cli.html
robotengine/docs/robotengine/engine.html
robotengine/docs/robotengine/example.html
robotengine/docs/robotengine/help_server.html
robotengine/docs/robotengine/ho_robot.html
robotengine/docs/robotengine/input.html
robotengine/docs/robotengine/node.html
robotengine/docs/robotengine/robot_link.html
robotengine/docs/robotengine/robotlink.html
robotengine/docs/robotengine/serial_io.html
robotengine/docs/robotengine/signal.html
robotengine/docs/robotengine/state_machine.html
robotengine/docs/robotengine/timer.html
robotengine/docs/robotengine/tools.html
robotengine-0.27.dist-info/LICENSE
robotengine-0.27.dist-info/METADATA
robotengine-0.27.dist-info/WHEEL
robotengine-0.27.dist-info/entry_points.txt
robotengine-0.27.dist-info/top_level.txt
robotengine-0.27.dist-info/RECORD
