Metadata-Version: 2.1
Name: robotengine
Version: 0.27
Summary: A easy-to-use robot framework
Home-page: https://github.com/EricSanchezok/robotengine
Author: EricSanchez
Author-email: niexiaohangeric@163.com
Classifier: Programming Language :: Python :: 3
Classifier: License :: OSI Approved :: MIT License
Classifier: Operating System :: OS Independent
License-File: LICENSE
Requires-Dist: pyserial>=0.5
Requires-Dist: inputs>=0.5
Requires-Dist: requests>=2.32.3
Requires-Dist: aiohttp>=3.10.11
Requires-Dist: fastapi>=0.115.6
Requires-Dist: uvicorn>=0.33.0
